pdf2textbox/__init__.py
pdf2textbox/pdf2textbox.py
pdf2textbox-0.4.3.dist-info/LICENSE.txt
pdf2textbox-0.4.3.dist-info/METADATA
pdf2textbox-0.4.3.dist-info/WHEEL
pdf2textbox-0.4.3.dist-info/entry_points.txt
pdf2textbox-0.4.3.dist-info/top_level.txt
pdf2textbox-0.4.3.dist-info/RECORD
