Metadata-Version: 2.1
Name: pdf2textbox
Version: 0.4.3
Summary: A PDF-to-text converter based on pdfminer2
Home-page: https://github.com/0LL13/pdf2textbox
Author: Oliver Stapel
Author-email: hardy.ecc95@gmail.com
License: MIT
Project-URL: Bug Reports, https://github.com/0LL13/pdf2textbox/issues
Project-URL: Source, https://github.com/0LL13/pdf2textbox
Keywords: PDF pdfminer2 PDFconversion text-processing
Platform: UNKNOWN
Classifier: Development Status :: 5 - Production/Stable
Classifier: Intended Audience :: Science/Research
Classifier: License :: OSI Approved :: MIT License
Classifier: Programming Language :: Python :: 3.6
Classifier: Programming Language :: Python :: 3.7
Classifier: Programming Language :: Python :: Implementation :: CPython
Classifier: Operating System :: POSIX :: Linux
Classifier: Topic :: Text Processing :: General
Requires-Dist: pdfminer2
Requires-Dist: requests
Provides-Extra: dev
Requires-Dist: check-manifest; extra == 'dev'
Provides-Extra: test
Requires-Dist: pytest-cov; extra == 'test'
